Workbook

Sheet Unit Economics
B2: Unit Economics — Inputs
B3: Subscription software business, monthly view. Select B6:C10 and run @unit-economics.
B5: Input | C5: Value | D5: Note
B6: New customers this month | C6: 500 | D6: Customers acquired in the period
B7: Sales and marketing spend | C7: 150000 | D7: Total S&M cost for the period
B8: Average revenue per customer (monthly) | C8: 80 | D8: ARPU
B9: Gross margin | C9: 0.75 | D9: Share of revenue left after cost to serve
B10: Monthly churn rate | C10: 0.04 | D10: Share of customers lost each month
B12: Yellow cells are inputs you can change. Copilot will build the analysis when you run the skill.

Sheet Unit Economics (Key)
B2: Unit Economics — Reference Calculation
B3: Live formulas off the Unit Economics inputs. Use this to check Copilot's output. Change an input and this updates too.
B5: Metric | C5: Value | D5: How it's calculated
B6: Customer acquisition cost (CAC) | C6: ='Unit Economics'!C7/'Unit Economics'!C6 -> 300 | D6: S&M spend / new customers
B7: Gross profit per customer (monthly) | C7: ='Unit Economics'!C8*'Unit Economics'!C9 -> 60 | D7: ARPU x gross margin
B8: Average customer lifetime (months) | C8: =IFERROR(1/'Unit Economics'!C10,"") -> 25 | D8: 1 / monthly churn
B9: Lifetime value (LTV) | C9: =C7*C8 -> 1500 | D9: Monthly gross profit per customer x lifetime
B10: LTV to CAC ratio | C10: =IFERROR(C9/C6,"") -> 5 | D10: LTV / CAC (3.0x+ is generally healthy)
B11: CAC payback period (months) | C11: =IFERROR(C6/C7,"") -> 5 | D11: CAC / monthly gross profit per customer

Sheet P&L Variance
B2: Monthly P&L — Actual vs Budget vs Prior
B3: Figures in US dollars. Run @variance-commentary on this sheet.
B5: Line item | C5: Actual | D5: Budget | E5: Prior Month
B6: Revenue | C6: 1240000 | D6: 1200000 | E6: 1180000
B7: Cost of revenue | C7: 306000 | D7: 300000 | E7: 295000
B8: Gross profit | C8: =C6-C7 -> 934000 | D8: =D6-D7 -> 900000 | E8: =E6-E7 -> 885000
B10: Operating expenses
B11: Sales & marketing | C11: 280000 | D11: 240000 | E11: 250000
B12: Research & development | C12: 210000 | D12: 205000 | E12: 200000
B13: General & administrative | C13: 165000 | D13: 150000 | E13: 152000
B14: Customer success | C14: 95000 | D14: 100000 | E14: 98000
B15: Total operating expenses | C15: =SUM(C11:C14) -> 750000 | D15: =SUM(D11:D14) -> 695000 | E15: =SUM(E11:E14) -> 700000
B17: Operating income | C17: =C8-C15 -> 184000 | D17: =D8-D15 -> 205000 | E17: =E8-E15 -> 185000

Sheet P&L Variance (Key)
B2: P&L Variance — Reference Calculation
B3: Variances and a materiality flag (> $10,000 or > 5% vs budget). Use this to check which lines the skill should call out.
B5: Line item | C5: Actual | D5: Budget | E5: $ vs Bud | F5: % vs Bud | G5: $ vs Prior | H5: % vs Prior | I5: Material?
B6: Revenue | C6: ='P&L Variance'!C6 -> 1240000 | D6: ='P&L Variance'!D6 -> 1200000 | E6: =C6-D6 -> 40000 | F6: =IFERROR((C6-D6)/ABS(D6),"") -> 0.033333333 | G6: ='P&L Variance'!C6-'P&L Variance'!E6 -> 60000 | H6: =IFERROR(('P&L Variance'!C6-'P&L Variance'!E6)/ABS('P&L Variance'!E6),"") -> 0.050847458 | I6: =IF(OR(ABS(E6)>10000,ABS(F6)>0.05),"Material","-") -> Material
B7: Cost of revenue | C7: ='P&L Variance'!C7 -> 306000 | D7: ='P&L Variance'!D7 -> 300000 | E7: =C7-D7 -> 6000 | F7: =IFERROR((C7-D7)/ABS(D7),"") -> 0.02 | G7: ='P&L Variance'!C7-'P&L Variance'!E7 -> 11000 | H7: =IFERROR(('P&L Variance'!C7-'P&L Variance'!E7)/ABS('P&L Variance'!E7),"") -> 0.037288136 | I7: =IF(OR(ABS(E7)>10000,ABS(F7)>0.05),"Material","-") -> -
B8: Gross profit | C8: ='P&L Variance'!C8 -> 934000 | D8: ='P&L Variance'!D8 -> 900000 | E8: =C8-D8 -> 34000 | F8: =IFERROR((C8-D8)/ABS(D8),"") -> 0.037777778 | G8: ='P&L Variance'!C8-'P&L Variance'!E8 -> 49000 | H8: =IFERROR(('P&L Variance'!C8-'P&L Variance'!E8)/ABS('P&L Variance'!E8),"") -> 0.055367232 | I8: =IF(OR(ABS(E8)>10000,ABS(F8)>0.05),"Material","-") -> Material
B9: Sales & marketing | C9: ='P&L Variance'!C11 -> 280000 | D9: ='P&L Variance'!D11 -> 240000 | E9: =C9-D9 -> 40000 | F9: =IFERROR((C9-D9)/ABS(D9),"") -> 0.16666667 | G9: ='P&L Variance'!C11-'P&L Variance'!E11 -> 30000 | H9: =IFERROR(('P&L Variance'!C11-'P&L Variance'!E11)/ABS('P&L Variance'!E11),"") -> 0.12 | I9: =IF(OR(ABS(E9)>10000,ABS(F9)>0.05),"Material","-") -> Material
B10: Research & development | C10: ='P&L Variance'!C12 -> 210000 | D10: ='P&L Variance'!D12 -> 205000 | E10: =C10-D10 -> 5000 | F10: =IFERROR((C10-D10)/ABS(D10),"") -> 0.024390244 | G10: ='P&L Variance'!C12-'P&L Variance'!E12 -> 10000 | H10: =IFERROR(('P&L Variance'!C12-'P&L Variance'!E12)/ABS('P&L Variance'!E12),"") -> 0.05 | I10: =IF(OR(ABS(E10)>10000,ABS(F10)>0.05),"Material","-") -> -
B11: General & administrative | C11: ='P&L Variance'!C13 -> 165000 | D11: ='P&L Variance'!D13 -> 150000 | E11: =C11-D11 -> 15000 | F11: =IFERROR((C11-D11)/ABS(D11),"") -> 0.1 | G11: ='P&L Variance'!C13-'P&L Variance'!E13 -> 13000 | H11: =IFERROR(('P&L Variance'!C13-'P&L Variance'!E13)/ABS('P&L Variance'!E13),"") -> 0.085526316 | I11: =IF(OR(ABS(E11)>10000,ABS(F11)>0.05),"Material","-") -> Material
B12: Customer success | C12: ='P&L Variance'!C14 -> 95000 | D12: ='P&L Variance'!D14 -> 100000 | E12: =C12-D12 -> -5000 | F12: =IFERROR((C12-D12)/ABS(D12),"") -> -0.05 | G12: ='P&L Variance'!C14-'P&L Variance'!E14 -> -3000 | H12: =IFERROR(('P&L Variance'!C14-'P&L Variance'!E14)/ABS('P&L Variance'!E14),"") -> -0.030612245 | I12: =IF(OR(ABS(E12)>10000,ABS(F12)>0.05),"Material","-") -> -
B13: Total operating expenses | C13: ='P&L Variance'!C15 -> 750000 | D13: ='P&L Variance'!D15 -> 695000 | E13: =C13-D13 -> 55000 | F13: =IFERROR((C13-D13)/ABS(D13),"") -> 0.079136691 | G13: ='P&L Variance'!C15-'P&L Variance'!E15 -> 50000 | H13: =IFERROR(('P&L Variance'!C15-'P&L Variance'!E15)/ABS('P&L Variance'!E15),"") -> 0.071428571 | I13: =IF(OR(ABS(E13)>10000,ABS(F13)>0.05),"Material","-") -> Material
B14: Operating income | C14: ='P&L Variance'!C17 -> 184000 | D14: ='P&L Variance'!D17 -> 205000 | E14: =C14-D14 -> -21000 | F14: =IFERROR((C14-D14)/ABS(D14),"") -> -0.10243902 | G14: ='P&L Variance'!C17-'P&L Variance'!E17 -> -1000 | H14: =IFERROR(('P&L Variance'!C17-'P&L Variance'!E17)/ABS('P&L Variance'!E17),"") -> -0.0054054054 | I14: =IF(OR(ABS(E14)>10000,ABS(F14)>0.05),"Material","-") -> Material
B16: Materiality is keyed to the variance vs budget, matching the skill's rule.
