Workbook

Sheet Start Here
B1: STRINGFEST ANALYTICS
B2: Copilot in Excel Skills — Starter Workbook
B3: A file to demo and test skills in Copilot for Excel. Two demos: one built-in finance skill, one custom skill you install.
B5: What's inside
B6: • Unit Economics — clean input block for the built-in @unit-economics skill (Demo 1).
B7: • Unit Economics (Key) — the same metrics worked out with live formulas, so you can check Copilot's answer.
B8: • P&L Variance — a monthly P&L (actual / budget / prior) for the custom @variance-commentary skill (Demo 2).
B9: • P&L Variance (Key) — variances and a materiality flag worked out with formulas, so you can check what should get flagged.
B11: Tip: hide or delete the two (Key) sheets before you run this live in front of an audience, so nobody peeks at the answers.
B13: Demo 1 — Use a built-in skill (@unit-economics)
B14: 1. Go to the Unit Economics sheet. The yellow cells are the inputs.
B15: 2. Open Copilot, select the input range, and paste this prompt:
... B39: Skills need a Microsoft 365 Copilot license. Built-in finance skills are generally available across Excel for the web, Windows, and Mac. Custom skills rolled out to general availability through mid-2026; if you don't see the Custom skills tab, check the Insiders channel or your update status.

Sheet Unit Economics
B2: Unit Economics — Inputs
B3: Subscription software business, monthly view. Select B6:C10 and run @unit-economics.
B5: Input | C5: Value | D5: Note
B6: New customers this month | C6: 500 | D6: Customers acquired in the period
B7: Sales and marketing spend | C7: 150000 | D7: Total S&M cost for the period
B8: Average revenue per customer (monthly) | C8: 80 | D8: ARPU
B9: Gross margin | C9: 0.75 | D9: Share of revenue left after cost to serve
B10: Monthly churn rate | C10: 0.04 | D10: Share of customers lost each month
B12: Yellow cells are inputs you can change. Copilot will build the analysis when you run the skill.
B14: Unit Economics — Copilot Analysis
B15: Live formulas based on the yellow input cells above; change the inputs and this section recalculates.
B17: Metric | C17: Value | D17: Interpretation
B18: Customer acquisition cost (CAC) | C18: =C7/C6 -> 300 | D18: S&M spend divided by new customers acquired.
B19: Monthly gross profit per customer | C19: =C8*C9 -> 60 | D19: Monthly ARPU multiplied by gross margin.
B20: Average customer lifetime | C20: =1/C10 -> 25 | D20: Inverse of monthly churn rate.
B21: Lifetime value (LTV) | C21: =C8*C9/C10 -> 1500 | D21: Monthly gross profit per customer multiplied by expected lifetime.
B22: LTV to CAC ratio | C22: =(C8*C9/C10)/(C7/C6) -> 5 | D22: Above 3.0x is generally healthy; above 5.0x is strong.
B23: CAC payback period | C23: =(C7/C6)/(C8*C9) -> 5 | D23: Months required for gross profit to recover CAC.
B25: Health read
B26: =IF(C22>=3,"Healthy: LTV:CAC is "&TEXT(C22,"0.0x")&", above the 3.0x SaaS benchmark, and CAC payback is "&TEXT(C23,"0.0")&" months. The combination of $"&TEXT(C18,"#,##0")&" CAC, $"&TEXT(C21,"#,##0")&" LTV, and "&TEXT(C10,"0.0%")&" monthly churn points to attractive unit economics, assuming churn and acquisition efficiency hold.","Needs attention: LTV:CAC is "&TEXT(C22,"0.0x")&", below the 3.0x SaaS benchmark. Improve retention, ARPU, gross margin, or acquisition efficiency before scaling spend.") -> Healthy: LTV:CAC is 5.0x, above the 3.0x SaaS benchmark, and CAC payback is 5.0 months. The combination of $300 CAC, $1,500 LTV, and 4.0% monthly churn points to attractive unit economics, assuming churn and acquisition efficiency hold.

Sheet Unit Economics (Key)
B2: Unit Economics — Reference Calculation
B3: Live formulas off the Unit Economics inputs. Use this to check Copilot's output. Change an input and this updates too.
B5: Metric | C5: Value | D5: How it's calculated
B6: Customer acquisition cost (CAC) | C6: ='Unit Economics'!C7/'Unit Economics'!C6 -> 300 | D6: S&M spend / new customers
B7: Gross profit per customer (monthly) | C7: ='Unit Economics'!C8*'Unit Economics'!C9 -> 60 | D7: ARPU x gross margin
B8: Average customer lifetime (months) | C8: =IFERROR(1/'Unit Economics'!C10,"") -> 25 | D8: 1 / monthly churn
B9: Lifetime value (LTV) | C9: =C7*C8 -> 1500 | D9: Monthly gross profit per customer x lifetime
B10: LTV to CAC ratio | C10: =IFERROR(C9/C6,"") -> 5 | D10: LTV / CAC (3.0x+ is generally healthy)
B11: CAC payback period (months) | C11: =IFERROR(C6/C7,"") -> 5 | D11: CAC / monthly gross profit per customer

Sheet P&L Variance
B2: Monthly P&L — Actual vs Budget vs Prior | G2: Variance Commentary — Actual vs Budget vs Prior
B3: Figures in US dollars. Run @variance-commentary on this sheet. | G3: Materiality: flag budget variances greater than $10,000 or 5% of budget; table sorted by largest absolute budget variance.
B5: Line item | C5: Actual | D5: Budget | E5: Prior Month | G5: Line item | H5: Actual | I5: Budget | J5: $ vs Bud | K5: % vs Bud | L5: Prior Month | M5: $ vs Prior | N5: % vs Prior | O5: Abs $ vs Bud
B6: Revenue | C6: 1240000 | D6: 1200000 | E6: 1180000 | G6: =TRIM($B$15) -> Total operating expenses | H6: =$C$15 -> 750000 | I6: =$D$15 -> 695000 | J6: =H6-I6 -> 55000 | K6: =IFERROR(J6/I6,0) -> 0.079136691 | L6: =$E$15 -> 700000 | M6: =H6-L6 -> 50000 | N6: =IFERROR(M6/L6,0) -> 0.071428571 | O6: =ABS(J6) -> 55000
B7: Cost of revenue | C7: 306000 | D7: 300000 | E7: 295000 | G7: =TRIM($B$6) -> Revenue | H7: =$C$6 -> 1240000 | I7: =$D$6 -> 1200000 | J7: =H7-I7 -> 40000 | K7: =IFERROR(J7/I7,0) -> 0.033333333 | L7: =$E$6 -> 1180000 | M7: =H7-L7 -> 60000 | N7: =IFERROR(M7/L7,0) -> 0.050847458 | O7: =ABS(J7) -> 40000
B8: Gross profit | C8: =C6-C7 -> 934000 | D8: =D6-D7 -> 900000 | E8: =E6-E7 -> 885000 | G8: =TRIM($B$11) -> Sales & marketing | H8: =$C$11 -> 280000 | I8: =$D$11 -> 240000 | J8: =H8-I8 -> 40000 | K8: =IFERROR(J8/I8,0) -> 0.16666667 | L8: =$E$11 -> 250000 | M8: =H8-L8 -> 30000 | N8: =IFERROR(M8/L8,0) -> 0.12 | O8: =ABS(J8) -> 40000
G9: =TRIM($B$8) -> Gross profit | H9: =$C$8 -> 934000 | I9: =$D$8 -> 900000 | J9: =H9-I9 -> 34000 | K9: =IFERROR(J9/I9,0) -> 0.037777778 | L9: =$E$8 -> 885000 | M9: =H9-L9 -> 49000 | N9: =IFERROR(M9/L9,0) -> 0.055367232 | O9: =ABS(J9) -> 34000
B10: Operating expenses | G10: =TRIM($B$17) -> Operating income | H10: =$C$17 -> 184000 | I10: =$D$17 -> 205000 | J10: =H10-I10 -> -21000 | K10: =IFERROR(J10/I10,0) -> -0.10243902 | L10: =$E$17 -> 185000 | M10: =H10-L10 -> -1000 | N10: =IFERROR(M10/L10,0) -> -0.0054054054 | O10: =ABS(J10) -> 21000
B11: Sales & marketing | C11: 280000 | D11: 240000 | E11: 250000 | G11: =TRIM($B$13) -> General & administrative | H11: =$C$13 -> 165000 | I11: =$D$13 -> 150000 | J11: =H11-I11 -> 15000 | K11: =IFERROR(J11/I11,0) -> 0.1 | L11: =$E$13 -> 152000 | M11: =H11-L11 -> 13000 | N11: =IFERROR(M11/L11,0) -> 0.085526316 | O11: =ABS(J11) -> 15000
B12: Research & development | C12: 210000 | D12: 205000 | E12: 200000 | G12: =TRIM($B$7) -> Cost of revenue | H12: =$C$7 -> 306000 | I12: =$D$7 -> 300000 | J12: =H12-I12 -> 6000 | K12: =IFERROR(J12/I12,0) -> 0.02 | L12: =$E$7 -> 295000 | M12: =H12-L12 -> 11000 | N12: =IFERROR(M12/L12,0) -> 0.037288136 | O12: =ABS(J12) -> 6000
B13: General & administrative | C13: 165000 | D13: 150000 | E13: 152000 | G13: =TRIM($B$12) -> Research & development | H13: =$C$12 -> 210000 | I13: =$D$12 -> 205000 | J13: =H13-I13 -> 5000 | K13: =IFERROR(J13/I13,0) -> 0.024390244 | L13: =$E$12 -> 200000 | M13: =H13-L13 -> 10000 | N13: =IFERROR(M13/L13,0) -> 0.05 | O13: =ABS(J13) -> 5000
B14: Customer success | C14: 95000 | D14: 100000 | E14: 98000 | G14: =TRIM($B$14) -> Customer success | H14: =$C$14 -> 95000 | I14: =$D$14 -> 100000 | J14: =H14-I14 -> -5000 | K14: =IFERROR(J14/I14,0) -> -0.05 | L14: =$E$14 -> 98000 | M14: =H14-L14 -> -3000 | N14: =IFERROR(M14/L14,0) -> -0.030612245 | O14: =ABS(J14) -> 5000
B15: Total operating expenses | C15: =SUM(C11:C14) -> 750000 | D15: =SUM(D11:D14) -> 695000 | E15: =SUM(E11:E14) -> 700000
G16: Commentary
B17: Operating income | C17: =C8-C15 -> 184000 | D17: =D8-D15 -> 205000 | E17: =E8-E15 -> 185000 | G17: Total operating expenses were $55,000 over budget (+7.9%) and $50,000 above prior month (+7.1%), making expense growth the largest pressure point on the period.
G18: Revenue was $40,000 above budget (+3.3%) and $60,000 above prior month (+5.1%), showing stronger top-line activity than planned.
G19: Sales & marketing was $40,000 over budget (+16.7%) and $30,000 above prior month (+12.0%), suggesting incremental acquisition or campaign spend drove most of the expense overrun.
G20: Gross profit was $34,000 above budget (+3.8%) and $49,000 above prior month (+5.5%), consistent with revenue upside more than offsetting cost of revenue growth.
G21: Operating income was $21,000 below budget (-10.2%) and $1,000 below prior month (-0.5%), as the expense overrun absorbed nearly all of the revenue and gross profit upside.
G22: General & administrative was $15,000 over budget (+10.0%) and $13,000 above prior month (+8.6%), indicating overhead ran above plan.
G23: Overall, the month delivered healthy revenue and gross profit growth, but operating leverage did not flow through because operating expenses rose faster than plan. The main management focus is controlling sales & marketing and G&A spend so revenue upside converts into operating income.

Sheet P&L Variance (Key)
B2: P&L Variance — Reference Calculation
B3: Variances and a materiality flag (> $10,000 or > 5% vs budget). Use this to check which lines the skill should call out.
B5: Line item | C5: Actual | D5: Budget | E5: $ vs Bud | F5: % vs Bud | G5: $ vs Prior | H5: % vs Prior | I5: Material?
B6: Revenue | C6: ='P&L Variance'!C6 -> 1240000 | D6: ='P&L Variance'!D6 -> 1200000 | E6: =C6-D6 -> 40000 | F6: =IFERROR((C6-D6)/ABS(D6),"") -> 0.033333333 | G6: ='P&L Variance'!C6-'P&L Variance'!E6 -> 60000 | H6: =IFERROR(('P&L Variance'!C6-'P&L Variance'!E6)/ABS('P&L Variance'!E6),"") -> 0.050847458 | I6: =IF(OR(ABS(E6)>10000,ABS(F6)>0.05),"Material","-") -> Material
B7: Cost of revenue | C7: ='P&L Variance'!C7 -> 306000 | D7: ='P&L Variance'!D7 -> 300000 | E7: =C7-D7 -> 6000 | F7: =IFERROR((C7-D7)/ABS(D7),"") -> 0.02 | G7: ='P&L Variance'!C7-'P&L Variance'!E7 -> 11000 | H7: =IFERROR(('P&L Variance'!C7-'P&L Variance'!E7)/ABS('P&L Variance'!E7),"") -> 0.037288136 | I7: =IF(OR(ABS(E7)>10000,ABS(F7)>0.05),"Material","-") -> -
B8: Gross profit | C8: ='P&L Variance'!C8 -> 934000 | D8: ='P&L Variance'!D8 -> 900000 | E8: =C8-D8 -> 34000 | F8: =IFERROR((C8-D8)/ABS(D8),"") -> 0.037777778 | G8: ='P&L Variance'!C8-'P&L Variance'!E8 -> 49000 | H8: =IFERROR(('P&L Variance'!C8-'P&L Variance'!E8)/ABS('P&L Variance'!E8),"") -> 0.055367232 | I8: =IF(OR(ABS(E8)>10000,ABS(F8)>0.05),"Material","-") -> Material
B9: Sales & marketing | C9: ='P&L Variance'!C11 -> 280000 | D9: ='P&L Variance'!D11 -> 240000 | E9: =C9-D9 -> 40000 | F9: =IFERROR((C9-D9)/ABS(D9),"") -> 0.16666667 | G9: ='P&L Variance'!C11-'P&L Variance'!E11 -> 30000 | H9: =IFERROR(('P&L Variance'!C11-'P&L Variance'!E11)/ABS('P&L Variance'!E11),"") -> 0.12 | I9: =IF(OR(ABS(E9)>10000,ABS(F9)>0.05),"Material","-") -> Material
B10: Research & development | C10: ='P&L Variance'!C12 -> 210000 | D10: ='P&L Variance'!D12 -> 205000 | E10: =C10-D10 -> 5000 | F10: =IFERROR((C10-D10)/ABS(D10),"") -> 0.024390244 | G10: ='P&L Variance'!C12-'P&L Variance'!E12 -> 10000 | H10: =IFERROR(('P&L Variance'!C12-'P&L Variance'!E12)/ABS('P&L Variance'!E12),"") -> 0.05 | I10: =IF(OR(ABS(E10)>10000,ABS(F10)>0.05),"Material","-") -> -
B11: General & administrative | C11: ='P&L Variance'!C13 -> 165000 | D11: ='P&L Variance'!D13 -> 150000 | E11: =C11-D11 -> 15000 | F11: =IFERROR((C11-D11)/ABS(D11),"") -> 0.1 | G11: ='P&L Variance'!C13-'P&L Variance'!E13 -> 13000 | H11: =IFERROR(('P&L Variance'!C13-'P&L Variance'!E13)/ABS('P&L Variance'!E13),"") -> 0.085526316 | I11: =IF(OR(ABS(E11)>10000,ABS(F11)>0.05),"Material","-") -> Material
B12: Customer success | C12: ='P&L Variance'!C14 -> 95000 | D12: ='P&L Variance'!D14 -> 100000 | E12: =C12-D12 -> -5000 | F12: =IFERROR((C12-D12)/ABS(D12),"") -> -0.05 | G12: ='P&L Variance'!C14-'P&L Variance'!E14 -> -3000 | H12: =IFERROR(('P&L Variance'!C14-'P&L Variance'!E14)/ABS('P&L Variance'!E14),"") -> -0.030612245 | I12: =IF(OR(ABS(E12)>10000,ABS(F12)>0.05),"Material","-") -> -
B13: Total operating expenses | C13: ='P&L Variance'!C15 -> 750000 | D13: ='P&L Variance'!D15 -> 695000 | E13: =C13-D13 -> 55000 | F13: =IFERROR((C13-D13)/ABS(D13),"") -> 0.079136691 | G13: ='P&L Variance'!C15-'P&L Variance'!E15 -> 50000 | H13: =IFERROR(('P&L Variance'!C15-'P&L Variance'!E15)/ABS('P&L Variance'!E15),"") -> 0.071428571 | I13: =IF(OR(ABS(E13)>10000,ABS(F13)>0.05),"Material","-") -> Material
B14: Operating income | C14: ='P&L Variance'!C17 -> 184000 | D14: ='P&L Variance'!D17 -> 205000 | E14: =C14-D14 -> -21000 | F14: =IFERROR((C14-D14)/ABS(D14),"") -> -0.10243902 | G14: ='P&L Variance'!C17-'P&L Variance'!E17 -> -1000 | H14: =IFERROR(('P&L Variance'!C17-'P&L Variance'!E17)/ABS('P&L Variance'!E17),"") -> -0.0054054054 | I14: =IF(OR(ABS(E14)>10000,ABS(F14)>0.05),"Material","-") -> Material
B16: Materiality is keyed to the variance vs budget, matching the skill's rule.
